adafruit_ina260.py
adafruit_circuitpython_ina260-1.3.20.dist-info/licenses/LICENSE
adafruit_circuitpython_ina260-1.3.20.dist-info/METADATA
adafruit_circuitpython_ina260-1.3.20.dist-info/WHEEL
adafruit_circuitpython_ina260-1.3.20.dist-info/top_level.txt
adafruit_circuitpython_ina260-1.3.20.dist-info/RECORD
